pyloidal/__init__.py
pyloidal/_version.py
pyloidal/cocos.py
pyloidal-0.2.1.dist-info/LICENSE
pyloidal-0.2.1.dist-info/METADATA
pyloidal-0.2.1.dist-info/WHEEL
pyloidal-0.2.1.dist-info/top_level.txt
pyloidal-0.2.1.dist-info/RECORD
