Metadata-Version: 2.1
Name: pyloidal
Version: 0.2.1
Summary: Python utilies for tokamak science.
Author-email: Liam Pattinson <liam.pattinson@york.ac.uk>
License: MIT License
Project-URL: Source, https://github.com/PlasmaFAIR/pyloidal
Project-URL: Tracker, https://github.com/PlasmaFAIR/pyloidal/issues
Keywords: tokamak,cocos
Classifier: Programming Language :: Python
Classifier: Development Status :: 3 - Alpha
Classifier: Natural Language :: English
Classifier: Intended Audience :: Science/Research
Classifier: License :: OSI Approved :: MIT License
Classifier: Operating System :: OS Independent
Classifier: Programming Language :: Python
Classifier: Topic :: Software Development :: Libraries :: Python Modules
Classifier: Topic :: Scientific/Engineering :: Physics
Requires-Python: >=3.10
License-File: LICENSE
Requires-Dist: numpy >=1.24
Provides-Extra: lint
Requires-Dist: ruff ; extra == 'lint'
Requires-Dist: mypy ; extra == 'lint'
Provides-Extra: test
Requires-Dist: pytest ; extra == 'test'
Requires-Dist: coverage ; extra == 'test'
Requires-Dist: pytest-cov ; extra == 'test'
Requires-Dist: pytest-sugar ; extra == 'test'
